TrimMCStruct/__init__.py
TrimMCStruct/main.py
TrimMCStruct-0.0.5.9.dist-info/LICENSE(origin).md
TrimMCStruct-0.0.5.9.dist-info/LICENSE.md
TrimMCStruct-0.0.5.9.dist-info/METADATA
TrimMCStruct-0.0.5.9.dist-info/WHEEL
TrimMCStruct-0.0.5.9.dist-info/top_level.txt
TrimMCStruct-0.0.5.9.dist-info/RECORD
