Metadata-Version: 2.1
Name: TrimMCStruct
Version: 0.0.5.9
Summary: 读写操作《我的世界》.MCSTRUCTURE文件
Home-page: https://github.com/TriM-Organization/TrimMCStruct
Author: Eilles Wan, bgArray, phoenixr-codes(original author) 
Author-email: TriM-Organization@hotmail.com
Classifier: Intended Audience :: Developers
Classifier: Natural Language :: English
Classifier: License :: OSI Approved :: Apache Software License
Classifier: Operating System :: OS Independent
Classifier: Topic :: Software Development :: Libraries
Classifier: Programming Language :: Python
Classifier: Programming Language :: Python :: 3
Classifier: Programming Language :: Python :: 3.8
Classifier: Programming Language :: Python :: 3.9
Classifier: Programming Language :: Python :: 3.10
License-File: LICENSE(origin).md
License-File: LICENSE.md
Requires-Dist: numpy (>=1.21)
Requires-Dist: pynbt (>=2)
